haddock/__init__.py
haddock/curses_de.txt
haddock/curses_en.txt
haddock/curses_fr.txt
haddock/haddock.py
haddock_curses-0.1.6.dist-info/LICENSE
haddock_curses-0.1.6.dist-info/METADATA
haddock_curses-0.1.6.dist-info/WHEEL
haddock_curses-0.1.6.dist-info/RECORD
